{
  "images": {
    "bitnamisecure": {
      "amd64": {
        "size_mb": "220.37"
      },
      "arm64": {
        "size_mb": "206.07"
      },
      "detected_version": "1.25.4",
      "grype": {
        "critical": "0",
        "high": "0",
        "low": "0",
        "medium": "0"
      },
      "trivy": {
        "critical": "0",
        "high": "0",
        "low": "0",
        "medium": "0"
      }
    },
    "cg": {
      "amd64": {
        "size_mb": "249.44"
      },
      "arm64": {
        "size_mb": "236.78"
      },
      "detected_version": "1.25.4",
      "grype": {
        "critical": "0",
        "high": "0",
        "low": "0",
        "medium": "0"
      },
      "trivy": {
        "critical": "0",
        "high": "4",
        "low": "0",
        "medium": "8"
      }
    }
  },
  "upstream": {
    "version": "1.25.4"
  }
}