{
  "images": {
    "bitnamisecure": {
      "amd64": {
        "size_mb": "223.83"
      },
      "arm64": {
        "size_mb": "219.17"
      },
      "detected_version": "9.1.0",
      "grype": {
        "critical": "0",
        "high": "0",
        "low": "0",
        "medium": "1"
      },
      "trivy": {
        "critical": "0",
        "high": "0",
        "low": "0",
        "medium": "1"
      }
    },
    "cg": {
      "amd64": {
        "size_mb": "264.80"
      },
      "arm64": {
        "size_mb": "262.70"
      },
      "detected_version": "9.0.0",
      "grype": {
        "critical": "0",
        "high": "0",
        "low": "0",
        "medium": "0"
      },
      "trivy": {
        "critical": "0",
        "high": "0",
        "low": "0",
        "medium": "0"
      },
      "version_delay_days": 6
    }
  },
  "upstream": {
    "version": "9.1.0"
  }
}